rsd_database_model/__init__.py
rsd_database_model/alembic/env.py
rsd_database_model/alembic/README
rsd_database_model/alembic/script.py.mako
rsd_database_model/alembic/versions/3b91c7a8865e_add_catches_and_places_tables.py
rsd_database_model/alembic/versions/519b692dfb1f_change_bait_gear_and_others_columns_.py
rsd_database_model/alembic/versions/867090de2281_add_more_value_to_species_enum.py
rsd_database_model/alembic/versions/a23968c74480_add_weather_table.py
rsd_database_model/alembic/versions/a96b47a4b034_add_fisher_name_column_to_catches_table.py
rsd_database_model/alembic/versions/c84d54372353_change_name_column_length_in_places_.py
rsd_database_model/alembic.ini
rsd_database_model/tables/__init__.py
rsd_database_model/tables/base.py
rsd_database_model/tables/catches.py
rsd_database_model/tables/places.py
rsd_database_model/tables/weather.py
rsd_database_model-0.3.0.dist-info/WHEEL
rsd_database_model-0.3.0.dist-info/METADATA
rsd_database_model-0.3.0.dist-info/RECORD
