Metadata-Version: 2.1
Name: rsd-database-model
Version: 0.3.0
Summary: Database models for RSD catch analyser
Author: Pintér Tamás
Author-email: tamas.pinter@pannonszoftver.hu
Requires-Python: >=3.8,<4.0
Classifier: Programming Language :: Python :: 3
Classifier: Programming Language :: Python :: 3.10
Classifier: Programming Language :: Python :: 3.8
Classifier: Programming Language :: Python :: 3.9
